cybooster/__init__.py
cybooster/_boosterc.cpython-314-x86_64-linux-gnu.so
cybooster/_boosterc.pyx
cybooster/_ngboost.cpython-314-x86_64-linux-gnu.so
cybooster/_ngboost.pyx
cybooster/_ngboostclf.cpython-314-x86_64-linux-gnu.so
cybooster/_ngboostclf.pyx
cybooster/booster.py
cybooster/ngboost.py
cybooster/docs/conf.py
cybooster-0.7.1.dist-info/licenses/LICENSE
cybooster-0.7.1.dist-info/METADATA
cybooster-0.7.1.dist-info/WHEEL
cybooster-0.7.1.dist-info/top_level.txt
cybooster-0.7.1.dist-info/RECORD
