Metadata-Version: 2.4
Name: cybooster
Version: 0.7.1
Summary: A high-performance gradient boosting implementation using Cython
Author-email: "T. Moudiki" <thierry.moudiki@gmail.com>
License: The Clear BSD License
Project-URL: Homepage, https://github.com/Techtonique/cybooster
Project-URL: Source Code, https://github.com/Techtonique/cybooster
Project-URL: Bug Tracker, https://github.com/Techtonique/cybooster/issues
Platform: Linux
Platform: MacOS
Platform: Windows
Classifier: Development Status :: 4 - Beta
Classifier: Intended Audience :: Science/Research
Classifier: Intended Audience :: Developers
Classifier: License :: OSI Approved :: BSD License
Classifier: Operating System :: MacOS
Classifier: Operating System :: Microsoft :: Windows
Classifier: Operating System :: POSIX
Classifier: Programming Language :: Cython
Classifier: Programming Language :: Python :: 3.10
Classifier: Programming Language :: Python :: 3.11
Classifier: Programming Language :: Python :: 3.12
Classifier: Topic :: Software Development
Classifier: Topic :: Scientific/Engineering
Requires-Python: >=3.10
License-File: LICENSE
Requires-Dist: numpy>=2.0.0
Requires-Dist: scipy>=1.8.0
Requires-Dist: scikit-learn>=1.4.0
Requires-Dist: jax>=0.4.0
Requires-Dist: tqdm>=4.50.0
Requires-Dist: pandas>=2.0.0
Requires-Dist: nnetsauce
Provides-Extra: dev
Requires-Dist: black[jupyter]; extra == "dev"
Requires-Dist: build; extra == "dev"
Requires-Dist: pytest; extra == "dev"
Requires-Dist: ruff; extra == "dev"
Requires-Dist: setuptools-scm>=8; extra == "dev"
Requires-Dist: black[jupyter]; extra == "dev"
Requires-Dist: build; extra == "dev"
Requires-Dist: Cython; extra == "dev"
Requires-Dist: pytest; extra == "dev"
Requires-Dist: ruff; extra == "dev"
Requires-Dist: setuptools-scm>=8; extra == "dev"
Requires-Dist: sphinx; extra == "dev"
Requires-Dist: furo; extra == "dev"
Dynamic: license-file
Dynamic: platform
